setup.py
py_mess_0_server.egg-info/PKG-INFO
py_mess_0_server.egg-info/SOURCES.txt
py_mess_0_server.egg-info/dependency_links.txt
py_mess_0_server.egg-info/requires.txt
py_mess_0_server.egg-info/top_level.txt
server/__init__.py
server/server.py
server/server_gui.py
server/doc/__init__.py
server/doc/source/__init__.py
server/doc/source/conf.py
server/logs/__init__.py
server/logs/config_server_log.py
server/server/__init__.py
server/server/add_user.py
server/server/config_window.py
server/server/core.py
server/server/database.py
server/server/database_declarative.py
server/server/main_window.py
server/server/remove_user.py
server/server/stat_window.py
server/unit_tests/__init__.py
server/unit_tests/test_server.py
server/unit_tests/test_utils.py