Metadata-Version: 2.1
Name: py-mess-0-server
Version: 3.3.3
Summary: Mess Server
Home-page: UNKNOWN
Author: Sergey Kuznetsov
Author-email: ksn1974@mail.ru
License: UNKNOWN
Platform: UNKNOWN
